{
  "PlayerName": "Denis",
  "PlayerLevel": 2,
  "PlayerMoney": 63.0,
  "OccupiedPositions": [
    false,
    false,
    false
  ],
  "GameObjectDataList": [
    {
      "Id": 0,
      "X": 2082.07525189395,
      "Y": 281.63860017999764,
      "Width": 51.0,
      "Height": 96.0,
      "ImageSource": "pack://application:,,,/Data/NPC/down_idle_2_Gery.png",
      "Type": "NPC",
      "Name": "Gery",
      "Money": null,
      "Level": null
    },
    {
      "Id": 0,
      "X": 232.07525189395207,
      "Y": 281.63860017999764,
      "Width": 51.0,
      "Height": 96.0,
      "ImageSource": "pack://application:,,,/Data/NPC/down_idle_1_Miranda.png",
      "Type": "NPC",
      "Name": "Miranda",
      "Money": null,
      "Level": null
    },
    {
      "Id": 0,
      "X": 1132.0752518939469,
      "Y": -118.36139982000012,
      "Width": 51.0,
      "Height": 96.0,
      "ImageSource": "pack://application:,,,/Data/NPC/down_idle_1_Pedro.png",
      "Type": "NPC",
      "Name": "Pedro",
      "Money": null,
      "Level": null
    },
    {
      "Id": 0,
      "X": 1082.0752518939466,
      "Y": 981.63860017998945,
      "Width": 51.0,
      "Height": 96.0,
      "ImageSource": "pack://application:,,,/Data/NPC/down_idle_1_Lusia.png",
      "Type": "NPC",
      "Name": "Lusia",
      "Money": null,
      "Level": null
    },
    {
      "Id": 0,
      "X": 1532.0752518939378,
      "Y": 1881.6386001800277,
      "Width": 51.0,
      "Height": 96.0,
      "ImageSource": "pack://application:,,,/Data/NPC/down_idle_1_Jery.png",
      "Type": "NPC",
      "Name": "Jery",
      "Money": null,
      "Level": null
    },
    {
      "Id": 2,
      "X": 812.07525189395358,
      "Y": -602.36139981998554,
      "Width": 836.0,
      "Height": 456.0,
      "ImageSource": "pack://application:,,,/Data/item/Home_1.png",
      "Type": "HomeItem",
      "Name": null,
      "Money": null,
      "Level": null
    },
    {
      "Id": 3,
      "X": 2182.0752518939685,
      "Y": 31.638600180001383,
      "Width": 316.0,
      "Height": 556.0,
      "ImageSource": "pack://application:,,,/Data/item/Home_2.png",
      "Type": "HomeItem",
      "Name": null,
      "Money": null,
      "Level": null
    },
    {
      "Id": 4,
      "X": -117.92474810605002,
      "Y": 81.638600180002143,
      "Width": 316.0,
      "Height": 556.0,
      "ImageSource": "pack://application:,,,/Data/item/Home_3.png",
      "Type": "HomeItem",
      "Name": null,
      "Money": null,
      "Level": null
    },
    {
      "Id": 5,
      "X": 732.075251893956,
      "Y": 931.63860017999343,
      "Width": 316.0,
      "Height": 556.0,
      "ImageSource": "pack://application:,,,/Data/item/Home_4.png",
      "Type": "HomeItem",
      "Name": null,
      "Money": null,
      "Level": null
    },
    {
      "Id": 7,
      "X": 1832.0752518939239,
      "Y": 881.63860017999525,
      "Width": 368.0,
      "Height": 396.0,
      "ImageSource": "pack://application:,,,/Data/item/tree.png",
      "Type": "HomeItem",
      "Name": null,
      "Money": null,
      "Level": null
    },
    {
      "Id": 6,
      "X": 1532.0752518939378,
      "Y": 1281.6386001799749,
      "Width": 368.0,
      "Height": 396.0,
      "ImageSource": "pack://application:,,,/Data/item/tree.png",
      "Type": "TreeItem",
      "Name": null,
      "Money": null,
      "Level": null
    },
    {
      "Id": 8,
      "X": 2532.0752518940435,
      "Y": 1081.638600179979,
      "Width": 368.0,
      "Height": 396.0,
      "ImageSource": "pack://application:,,,/Data/item/tree.png",
      "Type": "TreeItem",
      "Name": null,
      "Money": null,
      "Level": null
    },
    {
      "Id": 9,
      "X": 2632.0752518940722,
      "Y": 81.638600180002143,
      "Width": 368.0,
      "Height": 396.0,
      "ImageSource": "pack://application:,,,/Data/item/tree.png",
      "Type": "TreeItem",
      "Name": null,
      "Money": null,
      "Level": null
    },
    {
      "Id": 10,
      "X": 2332.0752518940167,
      "Y": -718.361399819978,
      "Width": 368.0,
      "Height": 396.0,
      "ImageSource": "pack://application:,,,/Data/item/tree.png",
      "Type": "TreeItem",
      "Name": null,
      "Money": null,
      "Level": null
    },
    {
      "Id": 11,
      "X": 1732.0752518939214,
      "Y": -518.36139981999406,
      "Width": 368.0,
      "Height": 396.0,
      "ImageSource": "pack://application:,,,/Data/item/tree.png",
      "Type": "TreeItem",
      "Name": null,
      "Money": null,
      "Level": null
    },
    {
      "Id": 12,
      "X": 332.0752518939529,
      "Y": -918.36139981997144,
      "Width": 368.0,
      "Height": 396.0,
      "ImageSource": "pack://application:,,,/Data/item/tree.png",
      "Type": "TreeItem",
      "Name": null,
      "Money": null,
      "Level": null
    },
    {
      "Id": 13,
      "X": -467.92474810607496,
      "Y": -718.361399819978,
      "Width": 368.0,
      "Height": 396.0,
      "ImageSource": "pack://application:,,,/Data/item/tree.png",
      "Type": "TreeItem",
      "Name": null,
      "Money": null,
      "Level": null
    },
    {
      "Id": 14,
      "X": -567.92474810608053,
      "Y": -218.36139982000336,
      "Width": 368.0,
      "Height": 396.0,
      "ImageSource": "pack://application:,,,/Data/item/tree.png",
      "Type": "TreeItem",
      "Name": null,
      "Money": null,
      "Level": null
    },
    {
      "Id": 15,
      "X": 232.07525189395207,
      "Y": 1181.6386001799756,
      "Width": 368.0,
      "Height": 396.0,
      "ImageSource": "pack://application:,,,/Data/item/tree.png",
      "Type": "TreeItem",
      "Name": null,
      "Money": null,
      "Level": null
    },
    {
      "Id": 16,
      "X": -467.92474810607496,
      "Y": 1281.6386001799749,
      "Width": 368.0,
      "Height": 396.0,
      "ImageSource": "pack://application:,,,/Data/item/tree.png",
      "Type": "TreeItem",
      "Name": null,
      "Money": null,
      "Level": null
    },
    {
      "Id": 17,
      "X": -667.92474810608041,
      "Y": 681.63860018000275,
      "Width": 368.0,
      "Height": 396.0,
      "ImageSource": "pack://application:,,,/Data/item/tree.png",
      "Type": "TreeItem",
      "Name": null,
      "Money": null,
      "Level": null
    },
    {
      "Id": 1,
      "X": -2867.9247481057746,
      "Y": -3318.3613998198384,
      "Width": 8192.0,
      "Height": 8192.0,
      "ImageSource": "pack://application:,,,/Data/Map_6.png",
      "Type": "MapItem",
      "Name": null,
      "Money": null,
      "Level": null
    },
    {
      "Id": 1,
      "X": -1167.9247481059997,
      "Y": 2361.6386001801134,
      "Width": 4700.0,
      "Height": 100.0,
      "ImageSource": null,
      "Type": "Wall",
      "Name": null,
      "Money": null,
      "Level": null
    },
    {
      "Id": 2,
      "X": 3482.0752518942281,
      "Y": -1318.3613998199699,
      "Width": 100.0,
      "Height": 4700.0,
      "ImageSource": null,
      "Type": "Wall",
      "Name": null,
      "Money": null,
      "Level": null
    },
    {
      "Id": 3,
      "X": -1167.9247481059997,
      "Y": -1368.3613998199687,
      "Width": 4700.0,
      "Height": 100.0,
      "ImageSource": null,
      "Type": "Wall",
      "Name": null,
      "Money": null,
      "Level": null
    },
    {
      "Id": 4,
      "X": -1267.9247481059806,
      "Y": -1318.3613998199699,
      "Width": 100.0,
      "Height": 4700.0,
      "ImageSource": null,
      "Type": "Wall",
      "Name": null,
      "Money": null,
      "Level": null
    },
    {
      "Id": 5,
      "X": 1302.0752518939453,
      "Y": 831.63860017999718,
      "Width": 1680.0,
      "Height": 1000.0,
      "ImageSource": null,
      "Type": "WallSlow",
      "Name": null,
      "Money": null,
      "Level": null
    },
    {
      "Id": 6,
      "X": 1752.0752518939205,
      "Y": 431.63860017999906,
      "Width": 250.0,
      "Height": 500.0,
      "ImageSource": null,
      "Type": "WallSlow",
      "Name": null,
      "Money": null,
      "Level": null
    },
    {
      "Id": 7,
      "X": 2602.0752518940571,
      "Y": -768.36139981997655,
      "Width": 370.0,
      "Height": 2000.0,
      "ImageSource": null,
      "Type": "WallSlow",
      "Name": null,
      "Money": null,
      "Level": null
    },
    {
      "Id": 8,
      "X": 2152.0752518939639,
      "Y": 31.638600180001383,
      "Width": 500.0,
      "Height": 680.0,
      "ImageSource": null,
      "Type": "WallSlow",
      "Name": null,
      "Money": null,
      "Level": null
    },
    {
      "Id": 9,
      "X": -667.92474810608041,
      "Y": -768.36139981997655,
      "Width": 3400.0,
      "Height": 700.0,
      "ImageSource": null,
      "Type": "WallSlow",
      "Name": null,
      "Money": null,
      "Level": null
    },
    {
      "Id": 10,
      "X": 1752.0752518939205,
      "Y": -188.36139982000242,
      "Width": 250.0,
      "Height": 500.0,
      "ImageSource": null,
      "Type": "WallSlow",
      "Name": null,
      "Money": null,
      "Level": null
    },
    {
      "Id": 11,
      "X": 432.07525189395619,
      "Y": -188.36139982000242,
      "Width": 250.0,
      "Height": 500.0,
      "ImageSource": null,
      "Type": "WallSlow",
      "Name": null,
      "Money": null,
      "Level": null
    },
    {
      "Id": 12,
      "X": -667.92474810608041,
      "Y": -768.36139981997655,
      "Width": 520.0,
      "Height": 2400.0,
      "ImageSource": null,
      "Type": "WallSlow",
      "Name": null,
      "Money": null,
      "Level": null
    },
    {
      "Id": 13,
      "X": -187.92474810605319,
      "Y": 61.638600180001887,
      "Width": 500.0,
      "Height": 680.0,
      "ImageSource": null,
      "Type": "WallSlow",
      "Name": null,
      "Money": null,
      "Level": null
    },
    {
      "Id": 14,
      "X": 432.07525189395619,
      "Y": 461.63860018,
      "Width": 250.0,
      "Height": 500.0,
      "ImageSource": null,
      "Type": "WallSlow",
      "Name": null,
      "Money": null,
      "Level": null
    },
    {
      "Id": 15,
      "X": -667.92474810608041,
      "Y": 831.63860017999718,
      "Width": 1800.0,
      "Height": 1000.0,
      "ImageSource": null,
      "Type": "WallSlow",
      "Name": null,
      "Money": null,
      "Level": null
    }
  ],
  "CharacterCardsData": []
}